MANIFEST.in
README.rst
setup.cfg
setup.py
citedby/__init__.py
citedby/citations.py
citedby/client.py
citedby/custom_query/__init__.py
citedby/custom_query/journal_titles.py
citedby/custom_query/templates/0000-0000.json
citedby/custom_query/templates/0001-3765.json
citedby/custom_query/templates/0004-2730.json
citedby/custom_query/templates/0004-2749.json
citedby/custom_query/templates/0004-2803.json
citedby/custom_query/templates/0004-282X.json
citedby/custom_query/templates/0011-5258.json
citedby/custom_query/templates/0016-3813.json
citedby/custom_query/templates/0016-7169.json
citedby/custom_query/templates/0026-1742.json
citedby/custom_query/templates/0034-8376.json
citedby/custom_query/templates/0034-8910.json
citedby/custom_query/templates/0035-001X.json
citedby/custom_query/templates/0036-3634.json
citedby/custom_query/templates/0044-5967.json
citedby/custom_query/templates/0066-782X.json
citedby/custom_query/templates/0071-1276.json
citedby/custom_query/templates/0073-4721.json
citedby/custom_query/templates/0074-0276.json
citedby/custom_query/templates/0100-1965.json
citedby/custom_query/templates/0101-2061.json
citedby/custom_query/templates/0101-2800.json
citedby/custom_query/templates/0101-3262.json
citedby/custom_query/templates/0101-4161.json
citedby/custom_query/templates/0101-4714.json
citedby/custom_query/templates/0101-546X.json
citedby/custom_query/templates/0101-6083.json
citedby/custom_query/templates/0101-7330.json
citedby/custom_query/templates/0102-0536.json
citedby/custom_query/templates/0102-0935.json
citedby/custom_query/templates/0102-311X.json
citedby/custom_query/templates/0102-3306.json
citedby/custom_query/templates/0102-4450.json
citedby/custom_query/templates/0102-4698.json
citedby/custom_query/templates/0102-6720.json
citedby/custom_query/templates/0102-7182.json
citedby/custom_query/templates/0102-8650.json
citedby/custom_query/templates/0103-2100.json
citedby/custom_query/templates/0103-2186.json
citedbyapi.egg-info/PKG-INFO
citedbyapi.egg-info/SOURCES.txt
citedbyapi.egg-info/dependency_links.txt
citedbyapi.egg-info/requires.txt
citedbyapi.egg-info/top_level.txt
