Metadata-Version: 1.1
Name: citedbyapi
Version: 1.11.3
Summary: SciELO CitedBy service SDK for Python
Home-page: http://github.com/scieloorg/citedbyapi
Author: SciELO
Author-email: scielo-dev@googlegroups.com
License: UNKNOWN
Platform: UNKNOWN
Classifier: Development Status :: 4 - Beta
Classifier: Intended Audience :: Developers
Classifier: Programming Language :: Python :: 3
